PythonJiqiXuexiZaixianZhinan/README.md
PythonJiqiXuexiZaixianZhinan/__init__.py
PythonJiqiXuexiZaixianZhinan/__main__.py
PythonJiqiXuexiZaixianZhinan/file.epub
PythonJiqiXuexiZaixianZhinan/index.html
PythonJiqiXuexiZaixianZhinan/css/__init__.py
PythonJiqiXuexiZaixianZhinan/css/annotations.css
PythonJiqiXuexiZaixianZhinan/css/main.css
PythonJiqiXuexiZaixianZhinan/css/normalize.css
PythonJiqiXuexiZaixianZhinan/css/popup.css
PythonJiqiXuexiZaixianZhinan/font/__init__.py
PythonJiqiXuexiZaixianZhinan/font/fontello.eot
PythonJiqiXuexiZaixianZhinan/font/fontello.svg
PythonJiqiXuexiZaixianZhinan/font/fontello.ttf
PythonJiqiXuexiZaixianZhinan/font/fontello.woff
PythonJiqiXuexiZaixianZhinan/img/__init__.py
PythonJiqiXuexiZaixianZhinan/img/annotator-glyph-sprite.png
PythonJiqiXuexiZaixianZhinan/img/annotator-icon-sprite.png
PythonJiqiXuexiZaixianZhinan/img/apple-touch-icon.png
PythonJiqiXuexiZaixianZhinan/img/cancelfullscreen.png
PythonJiqiXuexiZaixianZhinan/img/close.png
PythonJiqiXuexiZaixianZhinan/img/fullscreen.png
PythonJiqiXuexiZaixianZhinan/img/loader.gif
PythonJiqiXuexiZaixianZhinan/img/menu-icon.png
PythonJiqiXuexiZaixianZhinan/img/save.png
PythonJiqiXuexiZaixianZhinan/img/saved.png
PythonJiqiXuexiZaixianZhinan/img/settings-s.png
PythonJiqiXuexiZaixianZhinan/img/settings.png
PythonJiqiXuexiZaixianZhinan/img/star.png
PythonJiqiXuexiZaixianZhinan/js/__init__.py
PythonJiqiXuexiZaixianZhinan/js/epub.js
PythonJiqiXuexiZaixianZhinan/js/epub.min.js
PythonJiqiXuexiZaixianZhinan/js/epub.min.map
PythonJiqiXuexiZaixianZhinan/js/hooks.min.js
PythonJiqiXuexiZaixianZhinan/js/hooks.min.map
PythonJiqiXuexiZaixianZhinan/js/reader.js
PythonJiqiXuexiZaixianZhinan/js/reader.js.map
PythonJiqiXuexiZaixianZhinan/js/reader.min.js
PythonJiqiXuexiZaixianZhinan/js/reader.min.map
PythonJiqiXuexiZaixianZhinan/js/hooks/__init__.py
PythonJiqiXuexiZaixianZhinan/js/hooks/extensions/__init__.py
PythonJiqiXuexiZaixianZhinan/js/hooks/extensions/highlight.js
python_jiqi_xuexi_zaixian_zhinan-2024.3.5.0.dist-info/METADATA
python_jiqi_xuexi_zaixian_zhinan-2024.3.5.0.dist-info/WHEEL
python_jiqi_xuexi_zaixian_zhinan-2024.3.5.0.dist-info/entry_points.txt
python_jiqi_xuexi_zaixian_zhinan-2024.3.5.0.dist-info/top_level.txt
python_jiqi_xuexi_zaixian_zhinan-2024.3.5.0.dist-info/RECORD
